adafruit_mpu6050.py
adafruit_circuitpython_mpu6050-1.3.3.dist-info/licenses/LICENSE
adafruit_circuitpython_mpu6050-1.3.3.dist-info/METADATA
adafruit_circuitpython_mpu6050-1.3.3.dist-info/WHEEL
adafruit_circuitpython_mpu6050-1.3.3.dist-info/top_level.txt
adafruit_circuitpython_mpu6050-1.3.3.dist-info/RECORD
